lbconverter/__init__.py
lbconverter/converters/__init__.py
lbconverter/converters/coco_converter.py
lbconverter/converters/labelbox_converter.py
lbconverter/converters/yolo_converter.py
lbconverter-0.0.21.dist-info/LICENSE
lbconverter-0.0.21.dist-info/METADATA
lbconverter-0.0.21.dist-info/WHEEL
lbconverter-0.0.21.dist-info/top_level.txt
lbconverter-0.0.21.dist-info/RECORD
