Metadata-Version: 2.1
Name: lbconverter
Version: 0.0.21
Summary: module of classes to assist on getting model results to labelbox
Author: Gabe
Author-email: gunderwood@labelbox.com
Classifier: Programming Language :: Python :: 3
Classifier: License :: OSI Approved :: MIT License
Classifier: Operating System :: OS Independent
Requires-Python: >=3.6
License-File: LICENSE
Requires-Dist: labelbox[data]
Requires-Dist: ultralytics
